README.rst
setup.py
gerrit_mq/__init__.py
gerrit_mq/__main__.py
gerrit_mq/common.py
gerrit_mq/daemon.py
gerrit_mq/functions.py
gerrit_mq/master.py
gerrit_mq/orm.py
gerrit_mq/webfront.py
gerrit_mq.egg-info/PKG-INFO
gerrit_mq.egg-info/SOURCES.txt
gerrit_mq.egg-info/dependency_links.txt
gerrit_mq.egg-info/entry_points.txt
gerrit_mq.egg-info/requires.txt
gerrit_mq.egg-info/top_level.txt