Metadata-Version: 1.1
Name: gerrit-mq
Version: 0.3.0
Summary: Gerrit merge serializer
Home-page: https://github.com/cheshirekow/gerrit_mq
Author: Josh Bialkowski
Author-email: josh.bialkowski@gmail.com
License: UNKNOWN
Download-URL: https://github.com/cheshirekow/gerrit_mq/archive/0.3.0.tar.gz
Keywords: gerrit,continuous-integration
Platform: UNKNOWN
